milos_first_python_package/__init__.py
milos_first_python_package/add.py
milos_first_python_package/power.py
milos_first_python_package/subtract.py
milos_first_python_package/extras/__init__.py
milos_first_python_package/extras/divide.py
milos_first_python_package/extras/multiply.py
milos_first_python_package-0.0.2.dist-info/METADATA
milos_first_python_package-0.0.2.dist-info/WHEEL
milos_first_python_package-0.0.2.dist-info/top_level.txt
milos_first_python_package-0.0.2.dist-info/RECORD
